besos/IDF_class.py
besos/IO_Objects.py
besos/__init__.py
besos/besos_utils.py
besos/besostypes.py
besos/config.py
besos/dask_utils.py
besos/eplus_funcs.py
besos/eppy_funcs.py
besos/errors.py
besos/evaluator.py
besos/example_ui.py
besos/objectives.py
besos/optimizer.py
besos/parameters.py
besos/problem.py
besos/pyehub_funcs.py
besos/sampling.py
besos/.ipynb_checkpoints/besos_utils-checkpoint.py
besos/.ipynb_checkpoints/config-checkpoint.py
besos/.ipynb_checkpoints/eplus_funcs-checkpoint.py
besos/.ipynb_checkpoints/eppy_funcs-checkpoint.py
besos/.ipynb_checkpoints/evaluator-checkpoint.py
besos/.ipynb_checkpoints/parameters-checkpoint.py
besos/.ipynb_checkpoints/pyehub_funcs-checkpoint.py
besos/.ipynb_checkpoints/sampling-checkpoint.py
besos/__pycache__/IDF_class.cpython-38.pyc
besos/__pycache__/IO_Objects.cpython-38.pyc
besos/__pycache__/__init__.cpython-38.pyc
besos/__pycache__/besos_utils.cpython-38.pyc
besos/__pycache__/besostypes.cpython-38.pyc
besos/__pycache__/config.cpython-38.pyc
besos/__pycache__/dask_utils.cpython-38.pyc
besos/__pycache__/eplus_funcs.cpython-38.pyc
besos/__pycache__/eppy_funcs.cpython-38.pyc
besos/__pycache__/errors.cpython-38.pyc
besos/__pycache__/evaluator.cpython-38.pyc
besos/__pycache__/objectives.cpython-38.pyc
besos/__pycache__/optimizer.cpython-38.pyc
besos/__pycache__/parameters.cpython-38.pyc
besos/__pycache__/problem.cpython-38.pyc
besos/__pycache__/pyehub_funcs.cpython-38.pyc
besos/__pycache__/sampling.cpython-38.pyc
besos/__pycache__/weather.cpython-38.pyc
besos/data/Custom_Long_Fields.idd
besos/data/Energy+.schema.epJSON
besos/data/example_bad_idf.idf
besos/data/example_building.epJSON
besos/data/example_epw.epw
besos/data/example_idd.idd
besos/data/example_idf.idf
besos/data/example_xlsx.xlsx
besos/data/unexpanded.idf
besos-2.2.3.dist-info/LICENSE
besos-2.2.3.dist-info/METADATA
besos-2.2.3.dist-info/WHEEL
besos-2.2.3.dist-info/top_level.txt
besos-2.2.3.dist-info/RECORD
