Metadata-Version: 2.1
Name: besos
Version: 2.2.3
Summary: A library for Building and Energy Simulation, Optimization and Surrogate-modelling
Home-page: https://gitlab.com/energyincities/besos
Author: Ralph Evins
Author-email: revins@uvic.ca
Classifier: Programming Language :: Python :: 3
Classifier: License :: OSI Approved :: GNU General Public License (GPL)
Classifier: Operating System :: OS Independent
License-File: LICENSE
Requires-Dist: dask[complete]
Requires-Dist: Deprecated
Requires-Dist: eppy
Requires-Dist: geomeppy
Requires-Dist: matplotlib
Requires-Dist: numpy
Requires-Dist: packaging
Requires-Dist: pandas
Requires-Dist: platypus-opt
Requires-Dist: pyDOE2
Requires-Dist: pyehub ==1.5.0
Requires-Dist: rbfopt
Requires-Dist: Shapely
Requires-Dist: tqdm
Requires-Dist: PyYAML
Provides-Extra: complete
Requires-Dist: besos-examples ; extra == 'complete'
Requires-Dist: distributed ; extra == 'complete'
Requires-Dist: ipysheet ; extra == 'complete'
Requires-Dist: ipywidgets ; extra == 'complete'
Requires-Dist: joblib ; extra == 'complete'
Requires-Dist: jupyter ; extra == 'complete'
Requires-Dist: openpyxl ; extra == 'complete'
Requires-Dist: papermill ; extra == 'complete'
Requires-Dist: pvlib ; extra == 'complete'
Requires-Dist: pyKriging ; extra == 'complete'
Requires-Dist: SALib ; extra == 'complete'
Requires-Dist: scikit-learn ; extra == 'complete'
Requires-Dist: scipy ; extra == 'complete'
Requires-Dist: seaborn ; extra == 'complete'
Provides-Extra: dev
Requires-Dist: black ; extra == 'dev'
Requires-Dist: ipykernel ; extra == 'dev'
Requires-Dist: openpyxl ; extra == 'dev'
Requires-Dist: setuptools ; extra == 'dev'
Requires-Dist: py ; extra == 'dev'
Requires-Dist: pyKriging ; extra == 'dev'
Requires-Dist: pytest ; extra == 'dev'
Requires-Dist: pytest-cov ; extra == 'dev'
Requires-Dist: pytest-regtest ; extra == 'dev'
Requires-Dist: toolz ; extra == 'dev'
Requires-Dist: xlrd ==1.2.0 ; extra == 'dev'
